{
  "duration": 0.17369831900298596,
  "query": "PROFILE MATCH (p:MoocUser)\n                    MATCH (p)-[r:MoocAction]->()\n                    where r.TIMESTAMP >= 257126\n                    with p, count(r) as cnt\n                    where cnt >= 2\n                    return elementId(p), cnt",
  "profile": {
    "operatorType": "ProduceResults@neo4j",
    "identifiers": [
      "p",
      "cnt",
      "`elementId(p)`"
    ],
    "arguments": {
      "GlobalMemory": {
        "low": 852512,
        "high": 0
      },
      "planner-impl": "IDP",
      "Memory": {
        "low": 0,
        "high": 0
      },
      "string-representation": "Cypher 5\n\nPlanner COST\n\nRuntime SLOTTED\n\nRuntime version 5.22\n\n+---------------------------------------+----+-----------------------------------------------------------------------------------+----------------+--------+---------+----------------+------------------------+\n| Operator                              | Id | Details                                                                           | Estimated Rows | Rows   | DB Hits | Memory (Bytes) | Page Cache Hits/Misses |\n+---------------------------------------+----+-----------------------------------------------------------------------------------+----------------+--------+---------+----------------+------------------------+\n| +ProduceResults                       |  0 | `elementId(p)`, cnt                                                               |             33 |   6628 |       0 |              0 |                    0/0 |\n| |                                     +----+-----------------------------------------------------------------------------------+----------------+--------+---------+----------------+------------------------+\n| +Projection                           |  1 | elementId(p) AS `elementId(p)`                                                    |             33 |   6628 |       0 |                |                    0/0 |\n| |                                     +----+-----------------------------------------------------------------------------------+----------------+--------+---------+----------------+------------------------+\n| +Filter                               |  2 | cnt >= $autoint_1                                                                 |             33 |   6628 |       0 |                |                    0/0 |\n| |                                     +----+-----------------------------------------------------------------------------------+----------------+--------+---------+----------------+------------------------+\n| +EagerAggregation                     |  3 | p, count(r) AS cnt                                                                |            111 |   6667 |       0 |         852448 |                    0/0 |\n| |                                     +----+-----------------------------------------------------------------------------------+----------------+--------+---------+----------------+------------------------+\n| +Filter                               |  4 | p:MoocUser                                                                        |          12354 | 373947 |  373947 |                |                    0/0 |\n| |                                     +----+-----------------------------------------------------------------------------------+----------------+--------+---------+----------------+------------------------+\n| +DirectedRelationshipIndexSeekByRange |  5 | RANGE INDEX (p)-[r:MoocAction(TIMESTAMP)]->(anon_0) WHERE TIMESTAMP >= $autoint_0 |          12354 | 373947 |  373948 |                |                    0/0 |\n+---------------------------------------+----+-----------------------------------------------------------------------------------+----------------+--------+---------+----------------+------------------------+\n\nTotal database accesses: 747895, total allocated memory: 852512\n",
      "runtime": "SLOTTED",
      "runtime-impl": "SLOTTED",
      "version": "5",
      "DbHits": {
        "low": 0,
        "high": 0
      },
      "Details": "`elementId(p)`, cnt",
      "planner-version": "5.22",
      "runtime-version": "5.22",
      "Id": {
        "low": 0,
        "high": 0
      },
      "EstimatedRows": 33.344059583575316,
      "planner": "COST",
      "PageCacheMisses": {
        "low": 0,
        "high": 0
      },
      "Rows": {
        "low": 6628,
        "high": 0
      },
      "PageCacheHits": {
        "low": 0,
        "high": 0
      }
    },
    "dbHits": 0,
    "rows": 6628,
    "pageCacheMisses": 0,
    "pageCacheHits": 0,
    "pageCacheHitRatio": 0,
    "time": 0,
    "children": [
      {
        "operatorType": "Projection@neo4j",
        "identifiers": [
          "p",
          "cnt",
          "`elementId(p)`"
        ],
        "arguments": {
          "Details": "elementId(p) AS `elementId(p)`",
          "Id": {
            "low": 1,
            "high": 0
          },
          "PageCacheMisses": {
            "low": 0,
            "high": 0
          },
          "EstimatedRows": 33.344059583575316,
          "DbHits": {
            "low": 0,
            "high": 0
          },
          "Rows": {
            "low": 6628,
            "high": 0
          },
          "PageCacheHits": {
            "low": 0,
            "high": 0
          }
        },
        "dbHits": 0,
        "rows": 6628,
        "pageCacheMisses": 0,
        "pageCacheHits": 0,
        "pageCacheHitRatio": 0,
        "time": 0,
        "children": [
          {
            "operatorType": "Filter@neo4j",
            "identifiers": [
              "p",
              "cnt"
            ],
            "arguments": {
              "Details": "cnt >= $autoint_1",
              "Id": {
                "low": 2,
                "high": 0
              },
              "PageCacheMisses": {
                "low": 0,
                "high": 0
              },
              "EstimatedRows": 33.344059583575316,
              "DbHits": {
                "low": 0,
                "high": 0
              },
              "Rows": {
                "low": 6628,
                "high": 0
              },
              "PageCacheHits": {
                "low": 0,
                "high": 0
              }
            },
            "dbHits": 0,
            "rows": 6628,
            "pageCacheMisses": 0,
            "pageCacheHits": 0,
            "pageCacheHitRatio": 0,
            "time": 0,
            "children": [
              {
                "operatorType": "EagerAggregation@neo4j",
                "identifiers": [
                  "p",
                  "cnt"
                ],
                "arguments": {
                  "Details": "p, count(r) AS cnt",
                  "Memory": {
                    "low": 852448,
                    "high": 0
                  },
                  "Id": {
                    "low": 3,
                    "high": 0
                  },
                  "EstimatedRows": 111.14686527858439,
                  "PageCacheMisses": {
                    "low": 0,
                    "high": 0
                  },
                  "DbHits": {
                    "low": 0,
                    "high": 0
                  },
                  "Rows": {
                    "low": 6667,
                    "high": 0
                  },
                  "PageCacheHits": {
                    "low": 0,
                    "high": 0
                  }
                },
                "dbHits": 0,
                "rows": 6667,
                "pageCacheMisses": 0,
                "pageCacheHits": 0,
                "pageCacheHitRatio": 0,
                "time": 0,
                "children": [
                  {
                    "operatorType": "Filter@neo4j",
                    "identifiers": [
                      "r",
                      "p",
                      "anon_0"
                    ],
                    "arguments": {
                      "Details": "p:MoocUser",
                      "Id": {
                        "low": 4,
                        "high": 0
                      },
                      "PageCacheMisses": {
                        "low": 0,
                        "high": 0
                      },
                      "EstimatedRows": 12353.625661255786,
                      "DbHits": {
                        "low": 373947,
                        "high": 0
                      },
                      "Rows": {
                        "low": 373947,
                        "high": 0
                      },
                      "PageCacheHits": {
                        "low": 0,
                        "high": 0
                      }
                    },
                    "dbHits": 373947,
                    "rows": 373947,
                    "pageCacheMisses": 0,
                    "pageCacheHits": 0,
                    "pageCacheHitRatio": 0,
                    "time": 0,
                    "children": [
                      {
                        "operatorType": "DirectedRelationshipIndexSeekByRange@neo4j",
                        "identifiers": [
                          "r",
                          "p",
                          "anon_0"
                        ],
                        "arguments": {
                          "Details": "RANGE INDEX (p)-[r:MoocAction(TIMESTAMP)]->(anon_0) WHERE TIMESTAMP >= $autoint_0",
                          "Id": {
                            "low": 5,
                            "high": 0
                          },
                          "PageCacheMisses": {
                            "low": 0,
                            "high": 0
                          },
                          "EstimatedRows": 12353.625661255786,
                          "DbHits": {
                            "low": 373948,
                            "high": 0
                          },
                          "Rows": {
                            "low": 373947,
                            "high": 0
                          },
                          "PageCacheHits": {
                            "low": 0,
                            "high": 0
                          }
                        },
                        "dbHits": 373948,
                        "rows": 373947,
                        "pageCacheMisses": 0,
                        "pageCacheHits": 0,
                        "pageCacheHitRatio": 0,
                        "time": 0,
                        "children": []
                      }
                    ]
                  }
                ]
              }
            ]
          }
        ]
      }
    ]
  }
}