{
  "duration": 15.13634289199859,
  "query": "PROFILE MATCH (p:StableCoinAddress), (p)-[r:StableCoinAction]->()\n                    where r.value >= 200\n                    with p, count(r) as cnt\n                    where cnt >= 4\n                    return elementId(p), cnt",
  "profile": {
    "operatorType": "ProduceResults@neo4j",
    "identifiers": [
      "p",
      "cnt",
      "`elementId(p)`"
    ],
    "arguments": {
      "GlobalMemory": {
        "low": 266490840,
        "high": 0
      },
      "planner-impl": "IDP",
      "Memory": {
        "low": 0,
        "high": 0
      },
      "string-representation": "Cypher 5\n\nPlanner COST\n\nRuntime SLOTTED\n\nRuntime version 5.22\n\n+---------------------------------------+----+---------------------------------------------------------------------------------+----------------+----------+----------+----------------+------------------------+\n| Operator                              | Id | Details                                                                         | Estimated Rows | Rows     | DB Hits  | Memory (Bytes) | Page Cache Hits/Misses |\n+---------------------------------------+----+---------------------------------------------------------------------------------+----------------+----------+----------+----------------+------------------------+\n| +ProduceResults                       |  0 | `elementId(p)`, cnt                                                             |            199 |   258832 |        0 |              0 |                    0/0 |\n| |                                     +----+---------------------------------------------------------------------------------+----------------+----------+----------+----------------+------------------------+\n| +Projection                           |  1 | elementId(p) AS `elementId(p)`                                                  |            199 |   258832 |        0 |                |                    0/0 |\n| |                                     +----+---------------------------------------------------------------------------------+----------------+----------+----------+----------------+------------------------+\n| +Filter                               |  2 | cnt >= $autoint_1                                                               |            199 |   258832 |        0 |                |                    0/0 |\n| |                                     +----+---------------------------------------------------------------------------------+----------------+----------+----------+----------------+------------------------+\n| +EagerAggregation                     |  3 | p, count(r) AS cnt                                                              |            663 |  2239480 |        0 |      266490776 |                    0/0 |\n| |                                     +----+---------------------------------------------------------------------------------+----------------+----------+----------+----------------+------------------------+\n| +Filter                               |  4 | p:StableCoinAddress                                                             |         439511 | 10612836 | 10612836 |                |                    0/0 |\n| |                                     +----+---------------------------------------------------------------------------------+----------------+----------+----------+----------------+------------------------+\n| +DirectedRelationshipIndexSeekByRange |  5 | RANGE INDEX (p)-[r:StableCoinAction(value)]->(anon_0) WHERE value >= $autoint_0 |         439511 | 10612836 | 10612837 |                |                    0/0 |\n+---------------------------------------+----+---------------------------------------------------------------------------------+----------------+----------+----------+----------------+------------------------+\n\nTotal database accesses: 21225673, total allocated memory: 266490840\n",
      "runtime": "SLOTTED",
      "runtime-impl": "SLOTTED",
      "version": "5",
      "DbHits": {
        "low": 0,
        "high": 0
      },
      "Details": "`elementId(p)`, cnt",
      "planner-version": "5.22",
      "runtime-version": "5.22",
      "Id": {
        "low": 0,
        "high": 0
      },
      "EstimatedRows": 198.88682548650922,
      "planner": "COST",
      "PageCacheMisses": {
        "low": 0,
        "high": 0
      },
      "Rows": {
        "low": 258832,
        "high": 0
      },
      "PageCacheHits": {
        "low": 0,
        "high": 0
      }
    },
    "dbHits": 0,
    "rows": 258832,
    "pageCacheMisses": 0,
    "pageCacheHits": 0,
    "pageCacheHitRatio": 0,
    "time": 0,
    "children": [
      {
        "operatorType": "Projection@neo4j",
        "identifiers": [
          "p",
          "cnt",
          "`elementId(p)`"
        ],
        "arguments": {
          "Details": "elementId(p) AS `elementId(p)`",
          "Id": {
            "low": 1,
            "high": 0
          },
          "PageCacheMisses": {
            "low": 0,
            "high": 0
          },
          "EstimatedRows": 198.88682548650922,
          "DbHits": {
            "low": 0,
            "high": 0
          },
          "Rows": {
            "low": 258832,
            "high": 0
          },
          "PageCacheHits": {
            "low": 0,
            "high": 0
          }
        },
        "dbHits": 0,
        "rows": 258832,
        "pageCacheMisses": 0,
        "pageCacheHits": 0,
        "pageCacheHitRatio": 0,
        "time": 0,
        "children": [
          {
            "operatorType": "Filter@neo4j",
            "identifiers": [
              "p",
              "cnt"
            ],
            "arguments": {
              "Details": "cnt >= $autoint_1",
              "Id": {
                "low": 2,
                "high": 0
              },
              "PageCacheMisses": {
                "low": 0,
                "high": 0
              },
              "EstimatedRows": 198.88682548650922,
              "DbHits": {
                "low": 0,
                "high": 0
              },
              "Rows": {
                "low": 258832,
                "high": 0
              },
              "PageCacheHits": {
                "low": 0,
                "high": 0
              }
            },
            "dbHits": 0,
            "rows": 258832,
            "pageCacheMisses": 0,
            "pageCacheHits": 0,
            "pageCacheHitRatio": 0,
            "time": 0,
            "children": [
              {
                "operatorType": "EagerAggregation@neo4j",
                "identifiers": [
                  "p",
                  "cnt"
                ],
                "arguments": {
                  "Details": "p, count(r) AS cnt",
                  "Memory": {
                    "low": 266490776,
                    "high": 0
                  },
                  "Id": {
                    "low": 3,
                    "high": 0
                  },
                  "EstimatedRows": 662.9560849550307,
                  "PageCacheMisses": {
                    "low": 0,
                    "high": 0
                  },
                  "DbHits": {
                    "low": 0,
                    "high": 0
                  },
                  "Rows": {
                    "low": 2239480,
                    "high": 0
                  },
                  "PageCacheHits": {
                    "low": 0,
                    "high": 0
                  }
                },
                "dbHits": 0,
                "rows": 2239480,
                "pageCacheMisses": 0,
                "pageCacheHits": 0,
                "pageCacheHitRatio": 0,
                "time": 0,
                "children": [
                  {
                    "operatorType": "Filter@neo4j",
                    "identifiers": [
                      "r",
                      "p",
                      "anon_0"
                    ],
                    "arguments": {
                      "Details": "p:StableCoinAddress",
                      "Id": {
                        "low": 4,
                        "high": 0
                      },
                      "PageCacheMisses": {
                        "low": 0,
                        "high": 0
                      },
                      "EstimatedRows": 439510.7705789019,
                      "DbHits": {
                        "low": 10612836,
                        "high": 0
                      },
                      "Rows": {
                        "low": 10612836,
                        "high": 0
                      },
                      "PageCacheHits": {
                        "low": 0,
                        "high": 0
                      }
                    },
                    "dbHits": 10612836,
                    "rows": 10612836,
                    "pageCacheMisses": 0,
                    "pageCacheHits": 0,
                    "pageCacheHitRatio": 0,
                    "time": 0,
                    "children": [
                      {
                        "operatorType": "DirectedRelationshipIndexSeekByRange@neo4j",
                        "identifiers": [
                          "r",
                          "p",
                          "anon_0"
                        ],
                        "arguments": {
                          "Details": "RANGE INDEX (p)-[r:StableCoinAction(value)]->(anon_0) WHERE value >= $autoint_0",
                          "Id": {
                            "low": 5,
                            "high": 0
                          },
                          "PageCacheMisses": {
                            "low": 0,
                            "high": 0
                          },
                          "EstimatedRows": 439510.7705789019,
                          "DbHits": {
                            "low": 10612837,
                            "high": 0
                          },
                          "Rows": {
                            "low": 10612836,
                            "high": 0
                          },
                          "PageCacheHits": {
                            "low": 0,
                            "high": 0
                          }
                        },
                        "dbHits": 10612837,
                        "rows": 10612836,
                        "pageCacheMisses": 0,
                        "pageCacheHits": 0,
                        "pageCacheHitRatio": 0,
                        "time": 0,
                        "children": []
                      }
                    ]
                  }
                ]
              }
            ]
          }
        ]
      }
    ]
  }
}