{
  "duration": 24.769298078000546,
  "query": "PROFILE \n                    MATCH (n:StableCoinAddress)\n                    MATCH (n)-[r:StableCoinAction]->()\n                    where r.value >= 200\n                    WITH n, COLLECT(r.value) AS neighbors\n                    RETURN elementId(n), REDUCE(total = 0, val IN neighbors | total + val);\n                ",
  "profile": {
    "operatorType": "ProduceResults@neo4j",
    "identifiers": [
      "n",
      "neighbors",
      "`elementId(n)`",
      "`REDUCE(total = 0, val IN neighbors | total + val)`"
    ],
    "arguments": {
      "GlobalMemory": {
        "low": 850805072,
        "high": 0
      },
      "planner-impl": "IDP",
      "Memory": {
        "low": 0,
        "high": 0
      },
      "string-representation": "Cypher 5\n\nPlanner COST\n\nRuntime SLOTTED\n\nRuntime version 5.22\n\n+---------------------------------------+----+------------------------------------------------------------------------------------------------------+----------------+----------+----------+----------------+------------------------+\n| Operator                              | Id | Details                                                                                              | Estimated Rows | Rows     | DB Hits  | Memory (Bytes) | Page Cache Hits/Misses |\n+---------------------------------------+----+------------------------------------------------------------------------------------------------------+----------------+----------+----------+----------------+------------------------+\n| +ProduceResults                       |  0 | `elementId(n)`, `REDUCE(total = 0, val IN neighbors | total + val)`                                  |            663 |  2239480 |        0 |              0 |                    0/0 |\n| |                                     +----+------------------------------------------------------------------------------------------------------+----------------+----------+----------+----------------+------------------------+\n| +Projection                           |  1 | elementId(n) AS `elementId(n)`, reduce(total = $autoint_1, val IN neighbors | total + val) AS `REDUC |            663 |  2239480 |        0 |                |                    0/0 |\n| |                                     |    | E(total = 0, val IN neighbors | total + val)`                                                        |                |          |          |                |                        |\n| |                                     +----+------------------------------------------------------------------------------------------------------+----------------+----------+----------+----------------+------------------------+\n| +EagerAggregation                     |  2 | n, COLLECT(cache[r.value]) AS neighbors                                                              |            663 |  2239480 |        0 |      850805008 |                    0/0 |\n| |                                     +----+------------------------------------------------------------------------------------------------------+----------------+----------+----------+----------------+------------------------+\n| +Filter                               |  3 | n:StableCoinAddress                                                                                  |         439511 | 10612836 | 10612836 |                |                    0/0 |\n| |                                     +----+------------------------------------------------------------------------------------------------------+----------------+----------+----------+----------------+------------------------+\n| +DirectedRelationshipIndexSeekByRange |  4 | RANGE INDEX (n)-[r:StableCoinAction(value)]->(anon_0) WHERE value >= $autoint_0, cache[r.value]      |         439511 | 10612836 | 10612837 |                |                    0/0 |\n+---------------------------------------+----+------------------------------------------------------------------------------------------------------+----------------+----------+----------+----------------+------------------------+\n\nTotal database accesses: 21225673, total allocated memory: 850805072\n",
      "runtime": "SLOTTED",
      "runtime-impl": "SLOTTED",
      "version": "5",
      "DbHits": {
        "low": 0,
        "high": 0
      },
      "Details": "`elementId(n)`, `REDUCE(total = 0, val IN neighbors | total + val)`",
      "planner-version": "5.22",
      "runtime-version": "5.22",
      "Id": {
        "low": 0,
        "high": 0
      },
      "EstimatedRows": 662.9560849550307,
      "planner": "COST",
      "PageCacheMisses": {
        "low": 0,
        "high": 0
      },
      "Rows": {
        "low": 2239480,
        "high": 0
      },
      "PageCacheHits": {
        "low": 0,
        "high": 0
      }
    },
    "dbHits": 0,
    "rows": 2239480,
    "pageCacheMisses": 0,
    "pageCacheHits": 0,
    "pageCacheHitRatio": 0,
    "time": 0,
    "children": [
      {
        "operatorType": "Projection@neo4j",
        "identifiers": [
          "n",
          "neighbors",
          "`elementId(n)`",
          "`REDUCE(total = 0, val IN neighbors | total + val)`"
        ],
        "arguments": {
          "Details": "elementId(n) AS `elementId(n)`, reduce(total = $autoint_1, val IN neighbors | total + val) AS `REDUCE(total = 0, val IN neighbors | total + val)`",
          "Id": {
            "low": 1,
            "high": 0
          },
          "PageCacheMisses": {
            "low": 0,
            "high": 0
          },
          "EstimatedRows": 662.9560849550307,
          "DbHits": {
            "low": 0,
            "high": 0
          },
          "Rows": {
            "low": 2239480,
            "high": 0
          },
          "PageCacheHits": {
            "low": 0,
            "high": 0
          }
        },
        "dbHits": 0,
        "rows": 2239480,
        "pageCacheMisses": 0,
        "pageCacheHits": 0,
        "pageCacheHitRatio": 0,
        "time": 0,
        "children": [
          {
            "operatorType": "EagerAggregation@neo4j",
            "identifiers": [
              "n",
              "neighbors"
            ],
            "arguments": {
              "Details": "n, COLLECT(cache[r.value]) AS neighbors",
              "Memory": {
                "low": 850805008,
                "high": 0
              },
              "Id": {
                "low": 2,
                "high": 0
              },
              "EstimatedRows": 662.9560849550307,
              "PageCacheMisses": {
                "low": 0,
                "high": 0
              },
              "DbHits": {
                "low": 0,
                "high": 0
              },
              "Rows": {
                "low": 2239480,
                "high": 0
              },
              "PageCacheHits": {
                "low": 0,
                "high": 0
              }
            },
            "dbHits": 0,
            "rows": 2239480,
            "pageCacheMisses": 0,
            "pageCacheHits": 0,
            "pageCacheHitRatio": 0,
            "time": 0,
            "children": [
              {
                "operatorType": "Filter@neo4j",
                "identifiers": [
                  "r",
                  "n",
                  "anon_0"
                ],
                "arguments": {
                  "Details": "n:StableCoinAddress",
                  "Id": {
                    "low": 3,
                    "high": 0
                  },
                  "PageCacheMisses": {
                    "low": 0,
                    "high": 0
                  },
                  "EstimatedRows": 439510.7705789019,
                  "DbHits": {
                    "low": 10612836,
                    "high": 0
                  },
                  "Rows": {
                    "low": 10612836,
                    "high": 0
                  },
                  "PageCacheHits": {
                    "low": 0,
                    "high": 0
                  }
                },
                "dbHits": 10612836,
                "rows": 10612836,
                "pageCacheMisses": 0,
                "pageCacheHits": 0,
                "pageCacheHitRatio": 0,
                "time": 0,
                "children": [
                  {
                    "operatorType": "DirectedRelationshipIndexSeekByRange@neo4j",
                    "identifiers": [
                      "r",
                      "n",
                      "anon_0"
                    ],
                    "arguments": {
                      "Details": "RANGE INDEX (n)-[r:StableCoinAction(value)]->(anon_0) WHERE value >= $autoint_0, cache[r.value]",
                      "Id": {
                        "low": 4,
                        "high": 0
                      },
                      "PageCacheMisses": {
                        "low": 0,
                        "high": 0
                      },
                      "EstimatedRows": 439510.7705789019,
                      "DbHits": {
                        "low": 10612837,
                        "high": 0
                      },
                      "Rows": {
                        "low": 10612836,
                        "high": 0
                      },
                      "PageCacheHits": {
                        "low": 0,
                        "high": 0
                      }
                    },
                    "dbHits": 10612837,
                    "rows": 10612836,
                    "pageCacheMisses": 0,
                    "pageCacheHits": 0,
                    "pageCacheHitRatio": 0,
                    "time": 0,
                    "children": []
                  }
                ]
              }
            ]
          }
        ]
      }
    ]
  }
}